data/__init__.py
data/data_process.py
featureview/__init__.py
featureview/constant.py
featureview/exception.py
featureview/featureviewgui.py
featureview/util.py
featureview/data/__init__.py
featureview/data/data_process.py
featureview/ui/__init__.py
featureview/ui/resource_rc.py
featureview/ui/ui_login.py
featureview/ui/ui_search.py
featureview/ui/ui_xy.py
featureview/ui/ui_yt.py
featureview/widget/__init__.py
featureview/widget/birdview.py
featureview/widget/channel_tree.py
featureview/widget/login.py
featureview/widget/search.py
featureview/widget/xy.py
featureview/widget/yt.py
ui/__init__.py
ui/resource_rc.py
ui/ui_login.py
ui/ui_search.py
ui/ui_xy.py
ui/ui_yt.py
widget/__init__.py
widget/birdview.py
widget/channel_tree.py
widget/login.py
widget/search.py
widget/xy.py
widget/yt.py
featureview-1.0.4.1.dist-info/METADATA
featureview-1.0.4.1.dist-info/WHEEL
featureview-1.0.4.1.dist-info/entry_points.txt
featureview-1.0.4.1.dist-info/top_level.txt
featureview-1.0.4.1.dist-info/RECORD
