Metadata-Version: 2.1
Name: featureview
Version: 1.0.4.1
Summary: A tool for feature visualization
Home-page: UNKNOWN
Author: Jiahui Lu
Author-email: jiahui.lu.external@veoneer.com
License: UNKNOWN
Platform: UNKNOWN
Classifier: Programming Language :: Python :: 3.7
Classifier: Operating System :: Microsoft :: Windows :: Windows 10
Requires-Python: >=3.7.4, <=3.8
Requires-Dist: wheel
Requires-Dist: mdfreader (==3.3)
Requires-Dist: numpy (==1.17.4)
Requires-Dist: PyQt5 (==5.13.2)
Requires-Dist: pyqtgraph (==0.10.0)
